Workbook

Sheet Raw Income Statement
A1: USD millions | B1: FY2024 | C1: FY2025 | D1: FY2026
A2: Revenue | B2: 60922 | C2: 130497 | D2: 215938
A3: Cost of revenue | B3: 16621 | C3: 32639 | D3: 62475
A4: Gross profit | B4: 44301 | C4: 97858 | D4: 153463
A5: R&D | B5: 8675 | C5: 12914 | D5: 18497
A6: SG&A | B6: 2654 | C6: 3491 | D6: 4579
A7: Total operating expenses | B7: 11329 | C7: 16405 | D7: 23076
A8: Operating income | B8: 32972 | C8: 81453 | D8: 130387
A9: Interest income | B9: 866 | C9: 1786 | D9: 2300
A10: Interest expense | B10: -257 | C10: -247 | D10: -259
A11: Other income, net | B11: 237 | C11: 1034 | D11: 9022
A12: Total other income, net | B12: 846 | C12: 2573 | D12: 11063
A13: Income before tax | B13: 33818 | C13: 84026 | D13: 141450
... A15: Net income | B15: 29760 | C15: 72880 | D15: 120067

Sheet Raw Balance Sheet
A1: Particular | B1: FY2024 | C1: FY2025 | D1: FY2026
A2: Cash & cash equivalents | B2: 7280 | C2: 8589 | D2: 10605
A3: Marketable securities | B3: 18704 | C3: 34621 | D3: 51951
A4: Accounts receivable | B4: 9999 | C4: 23065 | D4: 38486
A5: Inventories | B5: 5282 | C5: 10080 | D5: 21403
A6: Prepaid expenses & other current assets | B6: 3080 | C6: 3771 | D6: 3180
A7: Total current assets | B7: 44345 | C7: 80126 | D7: 125605
A8: Accounts payable | B8: 2699 | C8: 6310 | D8: 9812
A9: Accrued & other current liabilities | B9: 6682 | C9: 11737 | D9: 21352
A10: Short-term debt | B10: 1250 | C10: — | D10: 999
A11: Total current liabilities | B11: 10631 | C11: 18047 | D11: 32163
A12: Long-term debt | B12: 8459 | C12: 8463 | D12: 7489
A13: Total Debt | B13: 9709 | C13: 8463 | D13: 8488
A14: Total liabilities | B14: 22750 | C14: 32274 | D14: 49510
A15: Total shareholders' equity | B15: 42978 | C15: 79327 | D15: 157293

Sheet Raw Cash Flow Statement
A1: Particular | B1: FY2024 | C1: FY2025 | D1: FY2026
A2: Net income | B2: 29760 | C2: 72880 | D2: 120067
A3: Depreciation & amortization | B3: 1508 | C3: 1864 | D3: 2843
A4: Stock-based compensation | B4: 3549 | C4: 4737 | D4: 6386
A5: Net cash provided by operating activities | B5: 28090 | C5: 64089 | D5: 102718
A6: Capital expenditure | B6: 1089 | C6: 3236 | D6: 6042
J11: s

Sheet Income Analysis
A1: NVIDIA Financial Performance Analysis
A3: Particular | B3: FY2024 | C3: FY2025 | D3: FY2026
A4: Revenue | B4: ='Raw Income Statement'!B2 -> 60922 | C4: ='Raw Income Statement'!C2 -> 130497 | D4: ='Raw Income Statement'!D2 -> 215938
A5: Gross Profit | B5: ='Raw Income Statement'!B4 -> 44301 | C5: ='Raw Income Statement'!C4 -> 97858 | D5: ='Raw Income Statement'!D4 -> 153463
A6: Total Operating Expenses | B6: ='Raw Income Statement'!B7 -> 11329 | C6: ='Raw Income Statement'!C7 -> 16405 | D6: ='Raw Income Statement'!D7 -> 23076
A7: Operating Income | B7: ='Raw Income Statement'!B8 -> 32972 | C7: ='Raw Income Statement'!C8 -> 81453 | D7: ='Raw Income Statement'!D8 -> 130387
A8: Income Before Tax | B8: ='Raw Income Statement'!B13 -> 33818 | C8: ='Raw Income Statement'!C13 -> 84026 | D8: ='Raw Income Statement'!D13 -> 141450
A9: Net Income | B9: ='Raw Income Statement'!B15 -> 29760 | C9: ='Raw Income Statement'!C15 -> 72880 | D9: ='Raw Income Statement'!D15 -> 120067
A11: Revenue Growth | B11: N/A | C11: =(C4 - B4) / B4 -> 1.1420341 | D11: =(D4 - C4) / C4 -> 0.65473536
A12: Gross Profit Growth | B12: N/A | C12: =(C5-B5)/B5 -> 1.2089343 | D12: =(D5-C5)/C5 -> 0.5682213
A13: Operating Income Growth | B13: N/A | C13: =(C7-B7)/B7 -> 1.4703688 | D13: =(D7-C7)/C7 -> 0.60076363
A14: Net Income Growth | B14: N/A | C14: =(C9-B9)/B9 -> 1.4489247 | D14: =(D9-C9)/C9 -> 0.64746158
A16: Gross Profit Margin | B16: =B5/B4 -> 0.72717573 | C16: =C5/C4 -> 0.74988697 | D16: =D5/D4 -> 0.71068084
A17: Operating Margin | B17: =B7/B4 -> 0.54121664 | C17: =C7/C4 -> 0.62417527 | D17: =D7/D4 -> 0.60381684
A18: Net Profit Margin | B18: =B9/B4 -> 0.48849348 | C18: =C9/C4 -> 0.55848027 | D18: =D9/D4 -> 0.55602534

Sheet Balance Sheet Analysis
A1: NVIDIA Balance Sheet Analysis
A3: Particular | B3: FY2024 | C3: FY2025 | D3: FY2026
A4: Cash & Cash Equivalents | B4: 7280 | C4: ='Raw Balance Sheet'!C2 -> 8589 | D4: ='Raw Balance Sheet'!D2 -> 10605
A5: Marketable Securities | B5: ='Raw Balance Sheet'!B3 -> 18704 | C5: ='Raw Balance Sheet'!C3 -> 34621 | D5: ='Raw Balance Sheet'!D3 -> 51951
A6: ='Raw Balance Sheet'!A4 -> Accounts receivable | B6: ='Raw Balance Sheet'!B4 -> 9999 | C6: ='Raw Balance Sheet'!C4 -> 23065 | D6: ='Raw Balance Sheet'!D4 -> 38486
A7: ='Raw Balance Sheet'!A5 -> Inventories | B7: ='Raw Balance Sheet'!B5 -> 5282 | C7: ='Raw Balance Sheet'!C5 -> 10080 | D7: ='Raw Balance Sheet'!D5 -> 21403
A8: ='Raw Balance Sheet'!A7 -> Total current assets | B8: ='Raw Balance Sheet'!B7 -> 44345 | C8: ='Raw Balance Sheet'!C7 -> 80126 | D8: ='Raw Balance Sheet'!D7 -> 125605
A10: ='Raw Balance Sheet'!A8 -> Accounts payable | B10: ='Raw Balance Sheet'!B8 -> 2699 | C10: ='Raw Balance Sheet'!C8 -> 6310 | D10: ='Raw Balance Sheet'!D8 -> 9812
A11: ='Raw Balance Sheet'!A9 -> Accrued & other current liabilities | B11: ='Raw Balance Sheet'!B9 -> 6682 | C11: ='Raw Balance Sheet'!C9 -> 11737 | D11: ='Raw Balance Sheet'!D9 -> 21352
A12: ='Raw Balance Sheet'!A10 -> Short-term debt | B12: ='Raw Balance Sheet'!B10 -> 1250 | C12: ='Raw Balance Sheet'!C10 -> — | D12: ='Raw Balance Sheet'!D10 -> 999
A13: ='Raw Balance Sheet'!A11 -> Total current liabilities | B13: ='Raw Balance Sheet'!B11 -> 10631 | C13: ='Raw Balance Sheet'!C11 -> 18047 | D13: ='Raw Balance Sheet'!D11 -> 32163
A15: ='Raw Balance Sheet'!A12 -> Long-term debt | B15: ='Raw Balance Sheet'!B12 -> 8459 | C15: ='Raw Balance Sheet'!C12 -> 8463 | D15: ='Raw Balance Sheet'!D12 -> 7489
A16: ='Raw Balance Sheet'!A13 -> Total Debt | B16: ='Raw Balance Sheet'!B13 -> 9709 | C16: ='Raw Balance Sheet'!C13 -> 8463 | D16: ='Raw Balance Sheet'!D13 -> 8488
A17: ='Raw Balance Sheet'!A14 -> Total liabilities | B17: ='Raw Balance Sheet'!B14 -> 22750 | C17: ='Raw Balance Sheet'!C14 -> 32274 | D17: ='Raw Balance Sheet'!D14 -> 49510
A18: ='Raw Balance Sheet'!A15 -> Total shareholders' equity | B18: ='Raw Balance Sheet'!B15 -> 42978 | C18: ='Raw Balance Sheet'!C15 -> 79327 | D18: ='Raw Balance Sheet'!D15 -> 157293
A20: Current Assets Growth | B20: N/A | C20: =(C8-B8)/B8 -> 0.80687789 | D20: =(D8-C8)/C8 -> 0.56759354
A21: Accounts Receivable Growth | B21: N/A | C21: =(C6-B6)/B6 -> 1.3067307 | D21: =(D6-C6)/C6 -> 0.66858877
A22: Inventory Growth | B22: N/A | C22: =(C7-B7)/B7 -> 0.90836804 | D22: =(D7-C7)/C7 -> 1.1233135
A23: Total Debt Growth | B23: N/A | C23: =(C16-B16)/B16 -> -0.12833453 | D23: =(D16-B16)/B16 -> -0.1257596
A25: Current Ratio | B25: =B8/B13 -> 4.1712915 | C25: =C8/C13 -> 4.4398515 | D25: =D8/D13 -> 3.9052638
A26: Quick Ratio | B26: =(B8-B7)/B13 -> 3.6744427 | C26: =(C8-C7)/C13 -> 3.8813099 | D26: =(D8-D7)/D13 -> 3.2398097
A27: Debt-to-Equity | B27: =B16/B18 -> 0.22590628 | C27: =C16/C18 -> 0.10668499 | D27: =D16/D18 -> 0.053962986
A28: Debt Ratio | B28: =B16/ (B16 + B18) -> 0.18427696 | C28: =C16/ (C16 + C18) -> 0.096400501 | D28: =D16/ (D16 + D18) -> 0.051200077
A29: Shareholders' Equity Growth | B29: N/A | C29: =(C18-B18)/B18 -> 0.84575829 | D29: =(D18-C18)/C18 -> 0.98284317

Sheet Cash Flow Analysis
A1: NVIDIA Cash Flow Analysis
A3: Particular | B3: FY2024 | C3: FY2025 | D3: FY2026
A4: Net Income | B4: ='Raw Cash Flow Statement'!B2 -> 29760 | C4: ='Raw Cash Flow Statement'!C2 -> 72880 | D4: ='Raw Cash Flow Statement'!D2 -> 120067
A5: Depreciation & Amortization | B5: ='Raw Cash Flow Statement'!B3 -> 1508 | C5: ='Raw Cash Flow Statement'!C3 -> 1864 | D5: ='Raw Cash Flow Statement'!D3 -> 2843
A6: Stock-Based Compensation | B6: ='Raw Cash Flow Statement'!B4 -> 3549 | C6: ='Raw Cash Flow Statement'!C4 -> 4737 | D6: ='Raw Cash Flow Statement'!D4 -> 6386
A7: Operating Cash Flow | B7: ='Raw Cash Flow Statement'!B5 -> 28090 | C7: ='Raw Cash Flow Statement'!C5 -> 64089 | D7: ='Raw Cash Flow Statement'!D5 -> 102718
A8: Capital Expenditure | B8: ='Raw Cash Flow Statement'!B6 -> 1089 | C8: ='Raw Cash Flow Statement'!C6 -> 3236 | D8: ='Raw Cash Flow Statement'!D6 -> 6042
A10: Free Cash Flow | B10: =B7+B8 -> 29179 | C10: =C7+C8 -> 67325 | D10: =D7+D8 -> 108760
A12: Operating Cash Flow Growth | B12: N/A | C12: =(C7-B7)/B7 -> 1.2815593 | D12: =(D7-C7)/C7 -> 0.60273994
A13: Free Cash Flow Growth | B13: N/A | C13: =(C10-B10)/B10 -> 1.3073101 | D13: =(D10-C10)/C10 -> 0.61544746
A15: Operating Cash Flow Margin | B15: ='Income Analysis'!B7 -> 32972 | C15: ='Income Analysis'!C7 -> 81453 | D15: ='Income Analysis'!D7 -> 130387
A16: Free Cash Flow Margin | B16: =B10/'Income Analysis'!B4 -> 0.4789567 | C16: =C10/'Income Analysis'!C4 -> 0.51591224 | D16: =D10/'Income Analysis'!D4 -> 0.50366309
A17: Operating Cash Flow / Net Income | B17: =B7/B4 -> 0.94388441 | C17: =C7/C4 -> 0.87937706 | D17: =D7/D4 -> 0.85550568

Sheet Dashboard
A1: NVIDIA FINANCIAL PERFORMANCE DASHBOARD
A2: Financial Performance Analysis | FY2024–FY2026
A4: Revenue FY2026 | E4: Net income FY2026 | I4: Operating cash flow FY2026 | M4: Free cash flow FY2026
A5: ='Income Analysis'!D4/1000 -> 215.938 | E5: ='Income Analysis'!D9/1000 -> 120.067 | I5: ='Cash Flow Analysis'!D7/1000 -> 102.718 | M5: ='Cash Flow Analysis'!D10/1000 -> 108.76
H21: Liquidity & Leverage
H22: Ratio | I22: FY2024 | J22: FY2025 | K22: FY2026
H23: Current Ratio | I23: 4.17x | J23: 4.44x | K23: 3.91x
H24: Quick Ratio | I24: 3.67x | J24: 3.88x | K24: 3.24x
H25: Debt-to-Equity | I25: 0.23x | J25: 0.11x | K25: 0.05x
H26: Debt Ratio | I26: 0.1843 | J26: 0.0964 | K26: 0.0512
A32: KEY INSIGHTS
A33: 1. Exceptional Revenue Growth
A34: Revenue increased from $60.9B in FY2024 to $215.9B in FY2026, with growth of 114.2% in FY2025 and 65.5% in FY2026, indicating sustained business expansion.
A36: 2. Strong Profitability
A37: Net profit margin improved from 48.9% in FY2024 to 55.6% in FY2026, while operating margin remained above 54%, demonstrating strong profitability.
A39: 3. Strong Cash Generation
A40: Operating cash flow increased from $28.1B to $102.7B between FY2024 and FY2026, indicating strong cash generation alongside earnings growth.
A42: 4. Working Capital Requires Monitoring
A43: Accounts receivable increased 130.7% in FY2025 and 66.9% in FY2026, while inventory grew 112.3% in FY2026. These trends highlight the importance of monitoring working-capital efficiency as the business scales.
A45: 5. Lower Financial Leverage
A46: Debt-to-equity declined from 0.23x in FY2024 to 0.05x in FY2026, while total debt remained relatively stable, indicating reduced reliance on debt financing relative to shareholders' equity.
